vyomcloudbridge/.DS_Store
vyomcloudbridge/__init__.py
vyomcloudbridge/cli.py
vyomcloudbridge/list_service.py
vyomcloudbridge/service_manager.py
vyomcloudbridge/setup.py
vyomcloudbridge/setup.sh
vyomcloudbridge/__pycache__/__init__.cpython-310.pyc
vyomcloudbridge/__pycache__/__init__.cpython-312.pyc
vyomcloudbridge/__pycache__/cli.cpython-310.pyc
vyomcloudbridge/__pycache__/cli.cpython-312.pyc
vyomcloudbridge/__pycache__/list_service.cpython-310.pyc
vyomcloudbridge/__pycache__/list_service.cpython-312.pyc
vyomcloudbridge/__pycache__/service_manager.cpython-310.pyc
vyomcloudbridge/__pycache__/service_manager.cpython-312.pyc
vyomcloudbridge/__pycache__/setup.cpython-310.pyc
vyomcloudbridge/__pycache__/setup.cpython-312.pyc
vyomcloudbridge/__pycache__/types.cpython-312.pyc
vyomcloudbridge/constants/__init__.py
vyomcloudbridge/constants/constants.py
vyomcloudbridge/constants/install_variable.py
vyomcloudbridge/constants/networks.json
vyomcloudbridge/constants/sample_image.jpg
vyomcloudbridge/constants/topics_list.py
vyomcloudbridge/constants/__pycache__/__init__.cpython-310.pyc
vyomcloudbridge/constants/__pycache__/__init__.cpython-312.pyc
vyomcloudbridge/constants/__pycache__/constants.cpython-310.pyc
vyomcloudbridge/constants/__pycache__/constants.cpython-312.pyc
vyomcloudbridge/constants/__pycache__/install_variable.cpython-310.pyc
vyomcloudbridge/constants/__pycache__/topics_list.cpython-312.pyc
vyomcloudbridge/data/__init__.py
vyomcloudbridge/data/vyom_data_type.py
vyomcloudbridge/listeners/__init__.py
vyomcloudbridge/listeners/awsiot_mqtt_listener.py
vyomcloudbridge/listeners/mav_listener.py
vyomcloudbridge/listeners/__pycache__/__init__.cpython-310.pyc
vyomcloudbridge/listeners/__pycache__/__init__.cpython-312.pyc
vyomcloudbridge/listeners/__pycache__/awsiot_mqtt_listener.cpython-310.pyc
vyomcloudbridge/listeners/__pycache__/awsiot_mqtt_listener.cpython-312.pyc
vyomcloudbridge/listeners/__pycache__/mav_listener.cpython-310.pyc
vyomcloudbridge-0.2.105.dist-info/licenses/LICENSE
vyomcloudbridge-0.2.105.dist-info/METADATA
vyomcloudbridge-0.2.105.dist-info/WHEEL
vyomcloudbridge-0.2.105.dist-info/entry_points.txt
vyomcloudbridge-0.2.105.dist-info/top_level.txt
vyomcloudbridge-0.2.105.dist-info/RECORD
