Metadata-Version: 2.4
Name: vyomcloudbridge
Version: 0.2.105
Summary: A communication service for vyom cloud
Author: Vyom OS Admin
Author-email: admin@vyomos.org
Requires-Python: >=3.6
License-File: LICENSE
Requires-Dist: awscrt>=0.23.5
Requires-Dist: awsiotsdk>=1.22.1
Requires-Dist: backports.tarfile>=1.2.0
Requires-Dist: build>=1.2.2.post1
Requires-Dist: catkin_pkg>=1.0.0
Requires-Dist: certifi>=2025.1.31
Requires-Dist: cffi>=1.17.1
Requires-Dist: charset-normalizer>=3.4.1
Requires-Dist: cryptography>=44.0.2
Requires-Dist: cv-bridge>=1.13.0.post0
Requires-Dist: docutils>=0.21.2
Requires-Dist: empy==3.3.4
Requires-Dist: future>=1.0.0
Requires-Dist: id>=1.5.0
Requires-Dist: idna>=3.10
Requires-Dist: importlib_metadata>=8.6.1
Requires-Dist: jaraco.classes>=3.4.0
Requires-Dist: jaraco.context>=6.0.1
Requires-Dist: jaraco.functools>=4.1.0
Requires-Dist: jeepney>=0.9.0
Requires-Dist: keyring>=25.6.0
Requires-Dist: lark-parser>=0.12.0
Requires-Dist: lockfile>=0.12.2
Requires-Dist: lxml>=5.3.2
Requires-Dist: markdown-it-py>=3.0.0
Requires-Dist: mdurl>=0.1.2
Requires-Dist: more-itertools>=10.7.0
Requires-Dist: nh3>=0.2.21
Requires-Dist: numpy<2.0,>=1.24.3
Requires-Dist: opencv-python<4.12,>=4.11.0.86
Requires-Dist: packaging>=25.0
Requires-Dist: paho-mqtt==2.1.0
Requires-Dist: pexpect>=4.9.0
Requires-Dist: pika>=1.3.2
Requires-Dist: psutil>=7.0.0
Requires-Dist: pycparser>=2.22
Requires-Dist: Pygments>=2.19.1
Requires-Dist: pymavlink>=2.4.47
Requires-Dist: pyproject_hooks>=1.2.0
Requires-Dist: pyserial>=3.5
Requires-Dist: python-daemon>=3.1.2
Requires-Dist: PyYAML>=6.0.2
Requires-Dist: readme_renderer>=44.0
Requires-Dist: requests-toolbelt>=1.0.0
Requires-Dist: requests>=2.32.3
Requires-Dist: rfc3986>=2.0.0
Requires-Dist: rich>=14.0.0
Requires-Dist: SecretStorage>=3.3.3
Requires-Dist: tomli>=2.2.1
Requires-Dist: twine>=6.1.0
Requires-Dist: typing_extensions>=4.13.2
Requires-Dist: urllib3>=2.4.0
Requires-Dist: zipp>=3.23.0
Dynamic: author
Dynamic: author-email
Dynamic: license-file
Dynamic: requires-dist
Dynamic: requires-python
Dynamic: summary
